README.md
setup.py
progress_py/__init__.py
progress_py/progress.py
progress_py.egg-info/PKG-INFO
progress_py.egg-info/SOURCES.txt
progress_py.egg-info/dependency_links.txt
progress_py.egg-info/top_level.txt