Metadata-Version: 1.0
Name: progress-py
Version: 1.1
Summary: Make customizable progress bars and spinners for cli
Home-page: UNKNOWN
Author: Priyansh Anand
Author-email: pr1y4nsh@protonmail.com
License: GPL
Platform: UNKNOWN
